Looper/__init__.py
cartesian_looper-0.1.dist-info/METADATA
cartesian_looper-0.1.dist-info/WHEEL
cartesian_looper-0.1.dist-info/top_level.txt
cartesian_looper-0.1.dist-info/RECORD
